{
  "version": "7",
  "dialect": "postgresql",
  "entries": [
    {
      "idx": 0,
      "version": "7",
      "when": 1757539038571,
      "tag": "20250910211718_lying_skrulls",
      "breakpoints": true
    },
    {
      "idx": 1,
      "version": "7",
      "when": 1757622946416,
      "tag": "20250911203546_little_tana_nile",
      "breakpoints": true
    },
    {
      "idx": 2,
      "version": "7",
      "when": 1757870585045,
      "tag": "20250914172305_cuddly_karen_page",
      "breakpoints": true
    },
    {
      "idx": 3,
      "version": "7",
      "when": 1757870862112,
      "tag": "20250914172742_warm_tigra",
      "breakpoints": true
    }
  ]
}